aspose/__init__.py
aspose/pycore.cp310-win32.pyd
aspose/pycore.cp311-win32.pyd
aspose/pycore.cp36-win32.pyd
aspose/pycore.cp37-win32.pyd
aspose/pycore.cp38-win32.pyd
aspose/pycore.cp39-win32.pyd
aspose/pydrawing.cp310-win32.pyd
aspose/pydrawing.cp311-win32.pyd
aspose/pydrawing.cp36-win32.pyd
aspose/pydrawing.cp37-win32.pyd
aspose/pydrawing.cp38-win32.pyd
aspose/pydrawing.cp39-win32.pyd
aspose/pygc.cp310-win32.pyd
aspose/pygc.cp311-win32.pyd
aspose/pygc.cp36-win32.pyd
aspose/pygc.cp37-win32.pyd
aspose/pygc.cp38-win32.pyd
aspose/pygc.cp39-win32.pyd
aspose/pyreflection.cp310-win32.pyd
aspose/pyreflection.cp311-win32.pyd
aspose/pyreflection.cp36-win32.pyd
aspose/pyreflection.cp37-win32.pyd
aspose/pyreflection.cp38-win32.pyd
aspose/pyreflection.cp39-win32.pyd
aspose/tex.cp310-win32.pyd
aspose/tex.cp311-win32.pyd
aspose/tex.cp36-win32.pyd
aspose/tex.cp37-win32.pyd
aspose/tex.cp38-win32.pyd
aspose/tex.cp39-win32.pyd
aspose/__pyinstaller/__init__.pyi
aspose/__pyinstaller/hook-aspose.py
aspose/assemblies/pycore/WrpInterop.Aspose.PyCore.dll
aspose/assemblies/pydrawing/Microsoft.Win32.SystemEvents.dll
aspose/assemblies/pydrawing/System.Drawing.Common.dll
aspose/assemblies/pydrawing/WrpInterop.Aspose.PyDrawing.dll
aspose/assemblies/pygc/Aspose.PyGC.dll
aspose/assemblies/pyreflection/WrpInterop.Aspose.PyReflection.dll
aspose/assemblies/tex/Aspose.TeX.dll
aspose/assemblies/tex/Microsoft.Win32.SystemEvents.dll
aspose/assemblies/tex/System.Drawing.Common.dll
aspose/assemblies/tex/System.Security.AccessControl.dll
aspose/assemblies/tex/System.Security.Permissions.dll
aspose/assemblies/tex/System.Security.Principal.Windows.dll
aspose/assemblies/tex/System.Windows.Extensions.dll
aspose/assemblies/tex/WrpInterop.Aspose.TeX.dll
aspose/netcore/netcore3.1/API-MS-Win-core-xstate-l2-1-0.dll
aspose/netcore/netcore3.1/Microsoft.CSharp.dll
aspose/netcore/netcore3.1/Microsoft.DiaSymReader.Native.x86.dll
aspose/netcore/netcore3.1/Microsoft.VisualBasic.Core.dll
Aspose.TeX-24.2.1.dist-info/METADATA
Aspose.TeX-24.2.1.dist-info/WHEEL
Aspose.TeX-24.2.1.dist-info/entry_points.txt
Aspose.TeX-24.2.1.dist-info/top_level.txt
Aspose.TeX-24.2.1.dist-info/RECORD
